{"2023":[{

    "ruralpercent": 1.2,
    "ruraltext": "20%",
    "ab": [{
        "base": 225.00,
        "spouse": 112.50,
        "first_single": 112.50,
        "child": 56.25
    }],
    "nb": [{
        "base": 95,
        "spouse": 47.50,
        "first_single": 47.50,
        "child": 23.75
    }],  
    "mb": [{
        "base": 150.00,
        "spouse": 75.00,
        "first_single": 75.00,
        "child": 37.50
    }],
    "nl": [{
        "base": 149.00,
        "spouse": 74.50,
        "first_single": 74.50,
        "child": 37.25
    }],
    "ns": [{
        "base": 103.00,
        "spouse": 51.50,
        "first_single": 51.50,
        "child": 25.75
    }],
    "on": [{
        "base": 140.00,
        "spouse": 70.00,
        "first_single": 70.00,
        "child": 35.00
    }],
    "pe": [{
        "base": 110.00,
        "spouse": 55.00,
        "first_single": 55.00,
        "child": 27.50
    }],
    "sk": [{
        "base": 188.00,
        "spouse": 94.00,
        "first_single": 94.00,
        "child": 47.00
    }]
}],
"pymntdate_e": "April 2024 to January 2025",
"pymntdate_f": "avril 2024 à janvier 2025"    
}
