{"data":[{

    "ruralpercent": 1.2,
    "ruraltext": "20%",
    "ab": [{
        "name_e": "Alberta",
        "name_f": "Alberta",
        "base": 225.00,
        "spouse": 112.50,
        "first_single": 112.50,
        "child": 56.25
    }],
    "nb": [{
        "name_e": "New Brunswick",
        "name_f": "Nouveau-Brunswick",
        "base": 95,
        "spouse": 47.50,
        "first_single": 47.50,
        "child": 23.75
    }],  
    "mb": [{
        "name_e": "Manitoba",
        "name_f": "Manitoba",
        "base": 150.00,
        "spouse": 75.00,
        "first_single": 75.00,
        "child": 37.50
    }],
    "nl": [{
        "name_e": "Newfoundland and Labrador",
        "name_f": "Terre-Neuve-et-Labrador",
        "base": 149.00,
        "spouse": 74.50,
        "first_single": 74.50,
        "child": 37.25
    }],
    "ns": [{
        "name_e": "Nova Scotia",
        "name_f": "Nouvelle-Écosse",
        "base": 103.00,
        "spouse": 51.50,
        "first_single": 51.50,
        "child": 25.75
    }],
    "on": [{
        "name_e": "Ontario",
        "name_f": "Ontario",
        "base": 140.00,
        "spouse": 70.00,
        "first_single": 70.00,
        "child": 35.00
    }],
    "pe": [{
        "name_e": "Prince Edward Island",
        "name_f": "Île-du-Prince-Édouard",
        "base": 110.00,
        "spouse": 55.00,
        "first_single": 55.00,
        "child": 27.50
    }],
    "sk": [{
        "name_e": "Saskatchewan",
        "name_f": "Saskatchewan",
        "base": 188.00,
        "spouse": 94.00,
        "first_single": 94.00,
        "child": 47.00
    }]
}],
"pymntdate_e": "April 2024 to January 2025",
    "pymntdate_f": "avril 2024 à janvier 2025"    
}
